Workbook
Name Products: Settings!$A$2:$A$6
Name LoanTypes: Settings!$B$2:$B$3
Name StatusList: Settings!$C$2:$C$7
Name StaffRoles: Settings!$D$2:$D$6
Name StaffNames: Settings!$E$2:$E$6
Name Channels: Settings!$F$2:$F$5
Name ExpenseCategories: Settings!$G$2:$G$7
Name ApplicationStatuses: Settings!$H$2:$H$8
Name RiskGrades: Settings!$I$2:$I$5
Name MeetingDays: Settings!$J$2:$J$8
Name PaymentTypes: Settings!$K$2:$K$5
Name LoanIDs: Loan_Register!$A$2:$A$301
Name ClientIDs: Client_Register!$A$2:$A$301
Name GroupIDs: Group_Register!$A$2:$A$201

Sheet README
A1: Microfinance Management Excel Template (Single Branch)
A3: This template follows the minimum registers and controls in the operating manuals (client register, group register, loan register, repayment ledger, cash book, receipt control, arrears log, bank reconciliation).
A5: Tip: If you need more rows, copy the last filled row downward (formulas + validation will extend).

Sheet Settings
A1: Products | B1: LoanTypes | C1: Statuses | D1: StaffRoles | E1: StaffNames | F1: Channels | G1: ExpenseCategories | H1: ApplicationStatuses | I1: RiskGrades | J1: MeetingDays | K1: PaymentTypes
A2: Group Loan 1 | B2: Group | C2: Draft | D2: Branch Manager | E2: (Edit Me) Dewmal | F2: SMS | G2: Transport | H2: Draft | I2: A | J2: Monday | K2: Installment
A3: Group Loan 2 | B3: Individual | C3: Active | D3: Loan Officer | E3: (Edit Me) Staff 2 | F3: Email | G3: Salary | H3: Submitted | I3: B | J3: Tuesday | K3: Fee
A4: Group Loan 3+ | C4: Closed | D4: Collections Officer | E4: (Edit Me) Staff 3 | F4: Call | G4: Utilities | H4: Under Review | I4: C | J4: Wednesday | K4: Penalty
A5: Individual Loan | C5: Rejected | D5: Finance/Cashier | E5: (Edit Me) Staff 4 | F5: WhatsApp | G5: Office Supplies | H5: Approved | I5: D | J5: Thursday | K5: Other
A6: Emergency Loan | C6: Watchlist | D6: Admin/Customer Service | E6: (Edit Me) Staff 5 | G6: Bank Charges | H6: Rejected | J6: Friday
C7: Written Off | G7: Other | H7: Cancelled | J7: Saturday
H8: Disbursed | J8: Sunday

Sheet Client_Register
A1: Client ID | B1: Full Name | C1: NIC | D1: Phone | E1: Address | F1: DOB | G1: Occupation | H1: Group ID | I1: Registration Date | J1: Status | K1: Notes
A2: =IF($B2="","", "C"&TEXT(ROW()-1,"0000"))
A3: =IF($B3="","", "C"&TEXT(ROW()-1,"0000"))
A4: =IF($B4="","", "C"&TEXT(ROW()-1,"0000"))
A5: =IF($B5="","", "C"&TEXT(ROW()-1,"0000"))
A6: =IF($B6="","", "C"&TEXT(ROW()-1,"0000"))
A7: =IF($B7="","", "C"&TEXT(ROW()-1,"0000"))
A8: =IF($B8="","", "C"&TEXT(ROW()-1,"0000"))
A9: =IF($B9="","", "C"&TEXT(ROW()-1,"0000"))
A10: =IF($B10="","", "C"&TEXT(ROW()-1,"0000"))
A11: =IF($B11="","", "C"&TEXT(ROW()-1,"0000"))
A12: =IF($B12="","", "C"&TEXT(ROW()-1,"0000"))
A13: =IF($B13="","", "C"&TEXT(ROW()-1,"0000"))
... A301: =IF($B301="","", "C"&TEXT(ROW()-1,"0000"))

Sheet Group_Register
A1: Group ID | B1: Member 1 Client ID | C1: Member 2 Client ID | D1: Member 3 Client ID | E1: Meeting Day | F1: Meeting Time | G1: Location | H1: Loan Officer | I1: Start Date | J1: Status | K1: Notes
A2: =IF($B2="","", "G"&TEXT(ROW()-1,"0000"))
A3: =IF($B3="","", "G"&TEXT(ROW()-1,"0000"))
A4: =IF($B4="","", "G"&TEXT(ROW()-1,"0000"))
A5: =IF($B5="","", "G"&TEXT(ROW()-1,"0000"))
A6: =IF($B6="","", "G"&TEXT(ROW()-1,"0000"))
A7: =IF($B7="","", "G"&TEXT(ROW()-1,"0000"))
A8: =IF($B8="","", "G"&TEXT(ROW()-1,"0000"))
A9: =IF($B9="","", "G"&TEXT(ROW()-1,"0000"))
A10: =IF($B10="","", "G"&TEXT(ROW()-1,"0000"))
A11: =IF($B11="","", "G"&TEXT(ROW()-1,"0000"))
A12: =IF($B12="","", "G"&TEXT(ROW()-1,"0000"))
A13: =IF($B13="","", "G"&TEXT(ROW()-1,"0000"))
... A201: =IF($B201="","", "G"&TEXT(ROW()-1,"0000"))

Sheet Loan_Application_Tracker
A1: Application ID | B1: Application Date | C1: Applicant Type | D1: Client/Group ID | E1: Product | F1: Requested Amount | G1: Term (Weeks) | H1: Proposed Installment | I1: Loan Officer | J1: Risk Grade | K1: Status | L1: Decision Date | M1: Approved Amount | N1: Approved By | O1: Notes
A2: =IF($D2="","", "APP"&TEXT(ROW()-1,"0000"))
A3: =IF($D3="","", "APP"&TEXT(ROW()-1,"0000"))
A4: =IF($D4="","", "APP"&TEXT(ROW()-1,"0000"))
A5: =IF($D5="","", "APP"&TEXT(ROW()-1,"0000"))
A6: =IF($D6="","", "APP"&TEXT(ROW()-1,"0000"))
A7: =IF($D7="","", "APP"&TEXT(ROW()-1,"0000"))
A8: =IF($D8="","", "APP"&TEXT(ROW()-1,"0000"))
A9: =IF($D9="","", "APP"&TEXT(ROW()-1,"0000"))
A10: =IF($D10="","", "APP"&TEXT(ROW()-1,"0000"))
A11: =IF($D11="","", "APP"&TEXT(ROW()-1,"0000"))
A12: =IF($D12="","", "APP"&TEXT(ROW()-1,"0000"))
A13: =IF($D13="","", "APP"&TEXT(ROW()-1,"0000"))
... A301: =IF($D301="","", "APP"&TEXT(ROW()-1,"0000"))

Sheet Loan_Register
A1: Loan ID | B1: Application ID | C1: Client/Group ID | D1: Product | E1: Loan Type | F1: Cycle | G1: Principal Amount | H1: Interest Method | I1: Interest Rate (%) | J1: Processing Fee | K1: Disbursement Date | L1: Tenor (Weeks) | M1: First Due Date | N1: Installment Amount | O1: Total Repayment | P1: Outstanding Balance | Q1: Next Due Date | R1: Status | S1: Loan Officer
A2: =IF($B2="","", "L"&TEXT(ROW()-1,"0000")) | M2: =IF($K2="","",$K2+7) | N2: =IF($O2="","", ROUND($O2/$L2,2)) | O2: =IF($G2="","", $G2*(1+$I2) + IF($J2="",0,$J2)) | P2: =IF($A2="","", $O2 - SUMIFS(Repayment_Ledger!$E$2:$E$801,Repayment_Ledger!$A$2:$A$801, $A2)) | Q2: =IF($P2<=0,"", MINIFS(Repayment_Ledger!$C$2:$C$801, Repayment_Ledger!$A$2:$A$801, $A2, Repayment_Ledger!$F$2:$F$801, "<>Paid"))
A3: =IF($B3="","", "L"&TEXT(ROW()-1,"0000")) | M3: =IF($K3="","",$K3+7) | N3: =IF($O3="","", ROUND($O3/$L3,2)) | O3: =IF($G3="","", $G3*(1+$I3) + IF($J3="",0,$J3)) | P3: =IF($A3="","", $O3 - SUMIFS(Repayment_Ledger!$E$2:$E$801,Repayment_Ledger!$A$2:$A$801, $A3)) | Q3: =IF($P3<=0,"", MINIFS(Repayment_Ledger!$C$2:$C$801, Repayment_Ledger!$A$2:$A$801, $A3, Repayment_Ledger!$F$2:$F$801, "<>Paid"))
A4: =IF($B4="","", "L"&TEXT(ROW()-1,"0000")) | M4: =IF($K4="","",$K4+7) | N4: =IF($O4="","", ROUND($O4/$L4,2)) | O4: =IF($G4="","", $G4*(1+$I4) + IF($J4="",0,$J4)) | P4: =IF($A4="","", $O4 - SUMIFS(Repayment_Ledger!$E$2:$E$801,Repayment_Ledger!$A$2:$A$801, $A4)) | Q4: =IF($P4<=0,"", MINIFS(Repayment_Ledger!$C$2:$C$801, Repayment_Ledger!$A$2:$A$801, $A4, Repayment_Ledger!$F$2:$F$801, "<>Paid"))
A5: =IF($B5="","", "L"&TEXT(ROW()-1,"0000")) | M5: =IF($K5="","",$K5+7) | N5: =IF($O5="","", ROUND($O5/$L5,2)) | O5: =IF($G5="","", $G5*(1+$I5) + IF($J5="",0,$J5)) | P5: =IF($A5="","", $O5 - SUMIFS(Repayment_Ledger!$E$2:$E$801,Repayment_Ledger!$A$2:$A$801, $A5)) | Q5: =IF($P5<=0,"", MINIFS(Repayment_Ledger!$C$2:$C$801, Repayment_Ledger!$A$2:$A$801, $A5, Repayment_Ledger!$F$2:$F$801, "<>Paid"))
A6: =IF($B6="","", "L"&TEXT(ROW()-1,"0000")) | M6: =IF($K6="","",$K6+7) | N6: =IF($O6="","", ROUND($O6/$L6,2)) | O6: =IF($G6="","", $G6*(1+$I6) + IF($J6="",0,$J6)) | P6: =IF($A6="","", $O6 - SUMIFS(Repayment_Ledger!$E$2:$E$801,Repayment_Ledger!$A$2:$A$801, $A6)) | Q6: =IF($P6<=0,"", MINIFS(Repayment_Ledger!$C$2:$C$801, Repayment_Ledger!$A$2:$A$801, $A6, Repayment_Ledger!$F$2:$F$801, "<>Paid"))
A7: =IF($B7="","", "L"&TEXT(ROW()-1,"0000")) | M7: =IF($K7="","",$K7+7) | N7: =IF($O7="","", ROUND($O7/$L7,2)) | O7: =IF($G7="","", $G7*(1+$I7) + IF($J7="",0,$J7)) | P7: =IF($A7="","", $O7 - SUMIFS(Repayment_Ledger!$E$2:$E$801,Repayment_Ledger!$A$2:$A$801, $A7)) | Q7: =IF($P7<=0,"", MINIFS(Repayment_Ledger!$C$2:$C$801, Repayment_Ledger!$A$2:$A$801, $A7, Repayment_Ledger!$F$2:$F$801, "<>Paid"))
A8: =IF($B8="","", "L"&TEXT(ROW()-1,"0000")) | M8: =IF($K8="","",$K8+7) | N8: =IF($O8="","", ROUND($O8/$L8,2)) | O8: =IF($G8="","", $G8*(1+$I8) + IF($J8="",0,$J8)) | P8: =IF($A8="","", $O8 - SUMIFS(Repayment_Ledger!$E$2:$E$801,Repayment_Ledger!$A$2:$A$801, $A8)) | Q8: =IF($P8<=0,"", MINIFS(Repayment_Ledger!$C$2:$C$801, Repayment_Ledger!$A$2:$A$801, $A8, Repayment_Ledger!$F$2:$F$801, "<>Paid"))
A9: =IF($B9="","", "L"&TEXT(ROW()-1,"0000")) | M9: =IF($K9="","",$K9+7) | N9: =IF($O9="","", ROUND($O9/$L9,2)) | O9: =IF($G9="","", $G9*(1+$I9) + IF($J9="",0,$J9)) | P9: =IF($A9="","", $O9 - SUMIFS(Repayment_Ledger!$E$2:$E$801,Repayment_Ledger!$A$2:$A$801, $A9)) | Q9: =IF($P9<=0,"", MINIFS(Repayment_Ledger!$C$2:$C$801, Repayment_Ledger!$A$2:$A$801, $A9, Repayment_Ledger!$F$2:$F$801, "<>Paid"))
A10: =IF($B10="","", "L"&TEXT(ROW()-1,"0000")) | M10: =IF($K10="","",$K10+7) | N10: =IF($O10="","", ROUND($O10/$L10,2)) | O10: =IF($G10="","", $G10*(1+$I10) + IF($J10="",0,$J10)) | P10: =IF($A10="","", $O10 - SUMIFS(Repayment_Ledger!$E$2:$E$801,Repayment_Ledger!$A$2:$A$801, $A10)) | Q10: =IF($P10<=0,"", MINIFS(Repayment_Ledger!$C$2:$C$801, Repayment_Ledger!$A$2:$A$801, $A10, Repayment_Ledger!$F$2:$F$801, "<>Paid"))
A11: =IF($B11="","", "L"&TEXT(ROW()-1,"0000")) | M11: =IF($K11="","",$K11+7) | N11: =IF($O11="","", ROUND($O11/$L11,2)) | O11: =IF($G11="","", $G11*(1+$I11) + IF($J11="",0,$J11)) | P11: =IF($A11="","", $O11 - SUMIFS(Repayment_Ledger!$E$2:$E$801,Repayment_Ledger!$A$2:$A$801, $A11)) | Q11: =IF($P11<=0,"", MINIFS(Repayment_Ledger!$C$2:$C$801, Repayment_Ledger!$A$2:$A$801, $A11, Repayment_Ledger!$F$2:$F$801, "<>Paid"))
A12: =IF($B12="","", "L"&TEXT(ROW()-1,"0000")) | M12: =IF($K12="","",$K12+7) | N12: =IF($O12="","", ROUND($O12/$L12,2)) | O12: =IF($G12="","", $G12*(1+$I12) + IF($J12="",0,$J12)) | P12: =IF($A12="","", $O12 - SUMIFS(Repayment_Ledger!$E$2:$E$801,Repayment_Ledger!$A$2:$A$801, $A12)) | Q12: =IF($P12<=0,"", MINIFS(Repayment_Ledger!$C$2:$C$801, Repayment_Ledger!$A$2:$A$801, $A12, Repayment_Ledger!$F$2:$F$801, "<>Paid"))
A13: =IF($B13="","", "L"&TEXT(ROW()-1,"0000")) | M13: =IF($K13="","",$K13+7) | N13: =IF($O13="","", ROUND($O13/$L13,2)) | O13: =IF($G13="","", $G13*(1+$I13) + IF($J13="",0,$J13)) | P13: =IF($A13="","", $O13 - SUMIFS(Repayment_Ledger!$E$2:$E$801,Repayment_Ledger!$A$2:$A$801, $A13)) | Q13: =IF($P13<=0,"", MINIFS(Repayment_Ledger!$C$2:$C$801, Repayment_Ledger!$A$2:$A$801, $A13, Repayment_Ledger!$F$2:$F$801, "<>Paid"))
... A301: =IF($B301="","", "L"&TEXT(ROW()-1,"0000")) | M301: =IF($K301="","",$K301+7) | N301: =IF($O301="","", ROUND($O301/$L301,2)) | O301: =IF($G301="","", $G301*(1+$I301) + IF($J301="",0,$J301)) | P301: =IF($A301="","", $O301 - SUMIFS(Repayment_Ledger!$E$2:$E$801,Repayment_Ledger!$A$2:$A$801, $A301)) | Q301: =IF($P301<=0,"", MINIFS(Repayment_Ledger!$C$2:$C$801, Repayment_Ledger!$A$2:$A$801, $A301, Repayment_Ledger!$F$2:$F$801, "<>Paid"))

Sheet Repayment_Ledger
A1: Loan ID | B1: Installment No | C1: Due Date | D1: Due Amount | E1: Paid Amount | F1: Payment Status | G1: Payment Date | H1: Receipt No | I1: Balance After Payment | J1: Days Past Due | K1: Collected By | L1: Notes
C2: =IF(AND($A2<>"",$B2<>""), XLOOKUP($A2,Loan_Register!$A$2:$A$301,Loan_Register!$M$2:$M$301,"") + 7*($B2-1), "") | D2: =IF($A2<>"", XLOOKUP($A2,Loan_Register!$A$2:$A$301,Loan_Register!$N$2:$N$301,""), "") | F2: =IF($A2="","", IF($E2>=$D2,"Paid", IF(TODAY()>$C2,"Overdue","Pending"))) | I2: =IF($A2="","", SUMIFS($D$2:$D$801,$A$2:$A$801,$A2) - SUMIFS($E$2:$E$801,$A$2:$A$801,$A2)) | J2: =IF($F2="Paid",0, IF($C2="","", MAX(0, TODAY()-$C2)))
C3: =IF(AND($A3<>"",$B3<>""), XLOOKUP($A3,Loan_Register!$A$2:$A$301,Loan_Register!$M$2:$M$301,"") + 7*($B3-1), "") | D3: =IF($A3<>"", XLOOKUP($A3,Loan_Register!$A$2:$A$301,Loan_Register!$N$2:$N$301,""), "") | F3: =IF($A3="","", IF($E3>=$D3,"Paid", IF(TODAY()>$C3,"Overdue","Pending"))) | I3: =IF($A3="","", SUMIFS($D$2:$D$801,$A$2:$A$801,$A3) - SUMIFS($E$2:$E$801,$A$2:$A$801,$A3)) | J3: =IF($F3="Paid",0, IF($C3="","", MAX(0, TODAY()-$C3)))
C4: =IF(AND($A4<>"",$B4<>""), XLOOKUP($A4,Loan_Register!$A$2:$A$301,Loan_Register!$M$2:$M$301,"") + 7*($B4-1), "") | D4: =IF($A4<>"", XLOOKUP($A4,Loan_Register!$A$2:$A$301,Loan_Register!$N$2:$N$301,""), "") | F4: =IF($A4="","", IF($E4>=$D4,"Paid", IF(TODAY()>$C4,"Overdue","Pending"))) | I4: =IF($A4="","", SUMIFS($D$2:$D$801,$A$2:$A$801,$A4) - SUMIFS($E$2:$E$801,$A$2:$A$801,$A4)) | J4: =IF($F4="Paid",0, IF($C4="","", MAX(0, TODAY()-$C4)))
C5: =IF(AND($A5<>"",$B5<>""), XLOOKUP($A5,Loan_Register!$A$2:$A$301,Loan_Register!$M$2:$M$301,"") + 7*($B5-1), "") | D5: =IF($A5<>"", XLOOKUP($A5,Loan_Register!$A$2:$A$301,Loan_Register!$N$2:$N$301,""), "") | F5: =IF($A5="","", IF($E5>=$D5,"Paid", IF(TODAY()>$C5,"Overdue","Pending"))) | I5: =IF($A5="","", SUMIFS($D$2:$D$801,$A$2:$A$801,$A5) - SUMIFS($E$2:$E$801,$A$2:$A$801,$A5)) | J5: =IF($F5="Paid",0, IF($C5="","", MAX(0, TODAY()-$C5)))
C6: =IF(AND($A6<>"",$B6<>""), XLOOKUP($A6,Loan_Register!$A$2:$A$301,Loan_Register!$M$2:$M$301,"") + 7*($B6-1), "") | D6: =IF($A6<>"", XLOOKUP($A6,Loan_Register!$A$2:$A$301,Loan_Register!$N$2:$N$301,""), "") | F6: =IF($A6="","", IF($E6>=$D6,"Paid", IF(TODAY()>$C6,"Overdue","Pending"))) | I6: =IF($A6="","", SUMIFS($D$2:$D$801,$A$2:$A$801,$A6) - SUMIFS($E$2:$E$801,$A$2:$A$801,$A6)) | J6: =IF($F6="Paid",0, IF($C6="","", MAX(0, TODAY()-$C6)))
C7: =IF(AND($A7<>"",$B7<>""), XLOOKUP($A7,Loan_Register!$A$2:$A$301,Loan_Register!$M$2:$M$301,"") + 7*($B7-1), "") | D7: =IF($A7<>"", XLOOKUP($A7,Loan_Register!$A$2:$A$301,Loan_Register!$N$2:$N$301,""), "") | F7: =IF($A7="","", IF($E7>=$D7,"Paid", IF(TODAY()>$C7,"Overdue","Pending"))) | I7: =IF($A7="","", SUMIFS($D$2:$D$801,$A$2:$A$801,$A7) - SUMIFS($E$2:$E$801,$A$2:$A$801,$A7)) | J7: =IF($F7="Paid",0, IF($C7="","", MAX(0, TODAY()-$C7)))
C8: =IF(AND($A8<>"",$B8<>""), XLOOKUP($A8,Loan_Register!$A$2:$A$301,Loan_Register!$M$2:$M$301,"") + 7*($B8-1), "") | D8: =IF($A8<>"", XLOOKUP($A8,Loan_Register!$A$2:$A$301,Loan_Register!$N$2:$N$301,""), "") | F8: =IF($A8="","", IF($E8>=$D8,"Paid", IF(TODAY()>$C8,"Overdue","Pending"))) | I8: =IF($A8="","", SUMIFS($D$2:$D$801,$A$2:$A$801,$A8) - SUMIFS($E$2:$E$801,$A$2:$A$801,$A8)) | J8: =IF($F8="Paid",0, IF($C8="","", MAX(0, TODAY()-$C8)))
C9: =IF(AND($A9<>"",$B9<>""), XLOOKUP($A9,Loan_Register!$A$2:$A$301,Loan_Register!$M$2:$M$301,"") + 7*($B9-1), "") | D9: =IF($A9<>"", XLOOKUP($A9,Loan_Register!$A$2:$A$301,Loan_Register!$N$2:$N$301,""), "") | F9: =IF($A9="","", IF($E9>=$D9,"Paid", IF(TODAY()>$C9,"Overdue","Pending"))) | I9: =IF($A9="","", SUMIFS($D$2:$D$801,$A$2:$A$801,$A9) - SUMIFS($E$2:$E$801,$A$2:$A$801,$A9)) | J9: =IF($F9="Paid",0, IF($C9="","", MAX(0, TODAY()-$C9)))
C10: =IF(AND($A10<>"",$B10<>""), XLOOKUP($A10,Loan_Register!$A$2:$A$301,Loan_Register!$M$2:$M$301,"") + 7*($B10-1), "") | D10: =IF($A10<>"", XLOOKUP($A10,Loan_Register!$A$2:$A$301,Loan_Register!$N$2:$N$301,""), "") | F10: =IF($A10="","", IF($E10>=$D10,"Paid", IF(TODAY()>$C10,"Overdue","Pending"))) | I10: =IF($A10="","", SUMIFS($D$2:$D$801,$A$2:$A$801,$A10) - SUMIFS($E$2:$E$801,$A$2:$A$801,$A10)) | J10: =IF($F10="Paid",0, IF($C10="","", MAX(0, TODAY()-$C10)))
C11: =IF(AND($A11<>"",$B11<>""), XLOOKUP($A11,Loan_Register!$A$2:$A$301,Loan_Register!$M$2:$M$301,"") + 7*($B11-1), "") | D11: =IF($A11<>"", XLOOKUP($A11,Loan_Register!$A$2:$A$301,Loan_Register!$N$2:$N$301,""), "") | F11: =IF($A11="","", IF($E11>=$D11,"Paid", IF(TODAY()>$C11,"Overdue","Pending"))) | I11: =IF($A11="","", SUMIFS($D$2:$D$801,$A$2:$A$801,$A11) - SUMIFS($E$2:$E$801,$A$2:$A$801,$A11)) | J11: =IF($F11="Paid",0, IF($C11="","", MAX(0, TODAY()-$C11)))
C12: =IF(AND($A12<>"",$B12<>""), XLOOKUP($A12,Loan_Register!$A$2:$A$301,Loan_Register!$M$2:$M$301,"") + 7*($B12-1), "") | D12: =IF($A12<>"", XLOOKUP($A12,Loan_Register!$A$2:$A$301,Loan_Register!$N$2:$N$301,""), "") | F12: =IF($A12="","", IF($E12>=$D12,"Paid", IF(TODAY()>$C12,"Overdue","Pending"))) | I12: =IF($A12="","", SUMIFS($D$2:$D$801,$A$2:$A$801,$A12) - SUMIFS($E$2:$E$801,$A$2:$A$801,$A12)) | J12: =IF($F12="Paid",0, IF($C12="","", MAX(0, TODAY()-$C12)))
C13: =IF(AND($A13<>"",$B13<>""), XLOOKUP($A13,Loan_Register!$A$2:$A$301,Loan_Register!$M$2:$M$301,"") + 7*($B13-1), "") | D13: =IF($A13<>"", XLOOKUP($A13,Loan_Register!$A$2:$A$301,Loan_Register!$N$2:$N$301,""), "") | F13: =IF($A13="","", IF($E13>=$D13,"Paid", IF(TODAY()>$C13,"Overdue","Pending"))) | I13: =IF($A13="","", SUMIFS($D$2:$D$801,$A$2:$A$801,$A13) - SUMIFS($E$2:$E$801,$A$2:$A$801,$A13)) | J13: =IF($F13="Paid",0, IF($C13="","", MAX(0, TODAY()-$C13)))
... C801: =IF(AND($A801<>"",$B801<>""), XLOOKUP($A801,Loan_Register!$A$2:$A$301,Loan_Register!$M$2:$M$301,"") + 7*($B801-1), "") | D801: =IF($A801<>"", XLOOKUP($A801,Loan_Register!$A$2:$A$301,Loan_Register!$N$2:$N$301,""), "") | F801: =IF($A801="","", IF($E801>=$D801,"Paid", IF(TODAY()>$C801,"Overdue","Pending"))) | I801: =IF($A801="","", SUMIFS($D$2:$D$801,$A$2:$A$801,$A801) - SUMIFS($E$2:$E$801,$A$2:$A$801,$A801)) | J801: =IF($F801="Paid",0, IF($C801="","", MAX(0, TODAY()-$C801)))

Sheet Receipt_Register
A1: Receipt No | B1: Date | C1: Loan ID | D1: Client ID | E1: Amount | F1: Payment Type | G1: Issued By | H1: Posted (Y/N) | I1: Notes
A2: =IF($C2="","", "R"&TEXT(ROW()-1,"00000"))
A3: =IF($C3="","", "R"&TEXT(ROW()-1,"00000"))
A4: =IF($C4="","", "R"&TEXT(ROW()-1,"00000"))
A5: =IF($C5="","", "R"&TEXT(ROW()-1,"00000"))
A6: =IF($C6="","", "R"&TEXT(ROW()-1,"00000"))
A7: =IF($C7="","", "R"&TEXT(ROW()-1,"00000"))
A8: =IF($C8="","", "R"&TEXT(ROW()-1,"00000"))
A9: =IF($C9="","", "R"&TEXT(ROW()-1,"00000"))
A10: =IF($C10="","", "R"&TEXT(ROW()-1,"00000"))
A11: =IF($C11="","", "R"&TEXT(ROW()-1,"00000"))
A12: =IF($C12="","", "R"&TEXT(ROW()-1,"00000"))
A13: =IF($C13="","", "R"&TEXT(ROW()-1,"00000"))
... A801: =IF($C801="","", "R"&TEXT(ROW()-1,"00000"))

Sheet Cash_Book
A1: Date | B1: Opening Cash | C1: Collections | D1: Other Receipts | E1: Expenses | F1: Deposits | G1: Closing Cash | H1: Verified By | I1: Notes
C2: =SUMIFS(Repayment_Ledger!$E$2:$E$801,Repayment_Ledger!$G$2:$G$801,$A2) | E2: =SUMIFS(Expense_Tracking!$F$2:$F$401,Expense_Tracking!$A$2:$A$401,$A2) | G2: =IF($A2="","", $B2+IF($C2="",0,$C2)+IF($D2="",0,$D2)-IF($E2="",0,$E2)-IF($F2="",0,$F2))
C3: =SUMIFS(Repayment_Ledger!$E$2:$E$801,Repayment_Ledger!$G$2:$G$801,$A3) | E3: =SUMIFS(Expense_Tracking!$F$2:$F$401,Expense_Tracking!$A$2:$A$401,$A3) | G3: =IF($A3="","", $B3+IF($C3="",0,$C3)+IF($D3="",0,$D3)-IF($E3="",0,$E3)-IF($F3="",0,$F3))
C4: =SUMIFS(Repayment_Ledger!$E$2:$E$801,Repayment_Ledger!$G$2:$G$801,$A4) | E4: =SUMIFS(Expense_Tracking!$F$2:$F$401,Expense_Tracking!$A$2:$A$401,$A4) | G4: =IF($A4="","", $B4+IF($C4="",0,$C4)+IF($D4="",0,$D4)-IF($E4="",0,$E4)-IF($F4="",0,$F4))
C5: =SUMIFS(Repayment_Ledger!$E$2:$E$801,Repayment_Ledger!$G$2:$G$801,$A5) | E5: =SUMIFS(Expense_Tracking!$F$2:$F$401,Expense_Tracking!$A$2:$A$401,$A5) | G5: =IF($A5="","", $B5+IF($C5="",0,$C5)+IF($D5="",0,$D5)-IF($E5="",0,$E5)-IF($F5="",0,$F5))
C6: =SUMIFS(Repayment_Ledger!$E$2:$E$801,Repayment_Ledger!$G$2:$G$801,$A6) | E6: =SUMIFS(Expense_Tracking!$F$2:$F$401,Expense_Tracking!$A$2:$A$401,$A6) | G6: =IF($A6="","", $B6+IF($C6="",0,$C6)+IF($D6="",0,$D6)-IF($E6="",0,$E6)-IF($F6="",0,$F6))
C7: =SUMIFS(Repayment_Ledger!$E$2:$E$801,Repayment_Ledger!$G$2:$G$801,$A7) | E7: =SUMIFS(Expense_Tracking!$F$2:$F$401,Expense_Tracking!$A$2:$A$401,$A7) | G7: =IF($A7="","", $B7+IF($C7="",0,$C7)+IF($D7="",0,$D7)-IF($E7="",0,$E7)-IF($F7="",0,$F7))
C8: =SUMIFS(Repayment_Ledger!$E$2:$E$801,Repayment_Ledger!$G$2:$G$801,$A8) | E8: =SUMIFS(Expense_Tracking!$F$2:$F$401,Expense_Tracking!$A$2:$A$401,$A8) | G8: =IF($A8="","", $B8+IF($C8="",0,$C8)+IF($D8="",0,$D8)-IF($E8="",0,$E8)-IF($F8="",0,$F8))
C9: =SUMIFS(Repayment_Ledger!$E$2:$E$801,Repayment_Ledger!$G$2:$G$801,$A9) | E9: =SUMIFS(Expense_Tracking!$F$2:$F$401,Expense_Tracking!$A$2:$A$401,$A9) | G9: =IF($A9="","", $B9+IF($C9="",0,$C9)+IF($D9="",0,$D9)-IF($E9="",0,$E9)-IF($F9="",0,$F9))
C10: =SUMIFS(Repayment_Ledger!$E$2:$E$801,Repayment_Ledger!$G$2:$G$801,$A10) | E10: =SUMIFS(Expense_Tracking!$F$2:$F$401,Expense_Tracking!$A$2:$A$401,$A10) | G10: =IF($A10="","", $B10+IF($C10="",0,$C10)+IF($D10="",0,$D10)-IF($E10="",0,$E10)-IF($F10="",0,$F10))
C11: =SUMIFS(Repayment_Ledger!$E$2:$E$801,Repayment_Ledger!$G$2:$G$801,$A11) | E11: =SUMIFS(Expense_Tracking!$F$2:$F$401,Expense_Tracking!$A$2:$A$401,$A11) | G11: =IF($A11="","", $B11+IF($C11="",0,$C11)+IF($D11="",0,$D11)-IF($E11="",0,$E11)-IF($F11="",0,$F11))
C12: =SUMIFS(Repayment_Ledger!$E$2:$E$801,Repayment_Ledger!$G$2:$G$801,$A12) | E12: =SUMIFS(Expense_Tracking!$F$2:$F$401,Expense_Tracking!$A$2:$A$401,$A12) | G12: =IF($A12="","", $B12+IF($C12="",0,$C12)+IF($D12="",0,$D12)-IF($E12="",0,$E12)-IF($F12="",0,$F12))
C13: =SUMIFS(Repayment_Ledger!$E$2:$E$801,Repayment_Ledger!$G$2:$G$801,$A13) | E13: =SUMIFS(Expense_Tracking!$F$2:$F$401,Expense_Tracking!$A$2:$A$401,$A13) | G13: =IF($A13="","", $B13+IF($C13="",0,$C13)+IF($D13="",0,$D13)-IF($E13="",0,$E13)-IF($F13="",0,$F13))
... C201: =SUMIFS(Repayment_Ledger!$E$2:$E$801,Repayment_Ledger!$G$2:$G$801,$A201) | E201: =SUMIFS(Expense_Tracking!$F$2:$F$401,Expense_Tracking!$A$2:$A$401,$A201) | G201: =IF($A201="","", $B201+IF($C201="",0,$C201)+IF($D201="",0,$D201)-IF($E201="",0,$E201)-IF($F201="",0,$F201))

Sheet Expense_Tracking
A1: Date | B1: Voucher No | C1: Paid To | D1: Category | E1: Description | F1: Amount | G1: Approved By | H1: Paid By | I1: Payment Method | J1: Notes
B2: =IF($A2="","", "PV"&TEXT(ROW()-1,"0000"))
B3: =IF($A3="","", "PV"&TEXT(ROW()-1,"0000"))
B4: =IF($A4="","", "PV"&TEXT(ROW()-1,"0000"))
B5: =IF($A5="","", "PV"&TEXT(ROW()-1,"0000"))
B6: =IF($A6="","", "PV"&TEXT(ROW()-1,"0000"))
B7: =IF($A7="","", "PV"&TEXT(ROW()-1,"0000"))
B8: =IF($A8="","", "PV"&TEXT(ROW()-1,"0000"))
B9: =IF($A9="","", "PV"&TEXT(ROW()-1,"0000"))
B10: =IF($A10="","", "PV"&TEXT(ROW()-1,"0000"))
B11: =IF($A11="","", "PV"&TEXT(ROW()-1,"0000"))
B12: =IF($A12="","", "PV"&TEXT(ROW()-1,"0000"))
B13: =IF($A13="","", "PV"&TEXT(ROW()-1,"0000"))
... B401: =IF($A401="","", "PV"&TEXT(ROW()-1,"0000"))

Sheet Bank_Deposit_Log
A1: Date | B1: Deposit Slip No | C1: Amount | D1: Source (Collections) | E1: Bank | F1: Entered By | G1: Checked By | H1: Notes

Sheet Bank_Reconciliation
A1: Recon Date | B1: Bank Statement Balance | C1: Cash Book Balance | D1: Deposits in Transit | E1: Outstanding Withdrawals | F1: Bank Charges | G1: Interest Earned | H1: Adjusted Bank Balance | I1: Adjusted Cash Book Balance | J1: Difference | K1: Reviewed By | L1: Notes
H2: =IF($A2="","", $B2+IF($D2="",0,$D2)-IF($E2="",0,$E2)-IF($F2="",0,$F2)+IF($G2="",0,$G2)) | I2: =IF($A2="","", $C2-IF($E2="",0,$E2)-IF($F2="",0,$F2)+IF($G2="",0,$G2)) | J2: =IF($A2="","", $H2-$I2)
H3: =IF($A3="","", $B3+IF($D3="",0,$D3)-IF($E3="",0,$E3)-IF($F3="",0,$F3)+IF($G3="",0,$G3)) | I3: =IF($A3="","", $C3-IF($E3="",0,$E3)-IF($F3="",0,$F3)+IF($G3="",0,$G3)) | J3: =IF($A3="","", $H3-$I3)
H4: =IF($A4="","", $B4+IF($D4="",0,$D4)-IF($E4="",0,$E4)-IF($F4="",0,$F4)+IF($G4="",0,$G4)) | I4: =IF($A4="","", $C4-IF($E4="",0,$E4)-IF($F4="",0,$F4)+IF($G4="",0,$G4)) | J4: =IF($A4="","", $H4-$I4)
H5: =IF($A5="","", $B5+IF($D5="",0,$D5)-IF($E5="",0,$E5)-IF($F5="",0,$F5)+IF($G5="",0,$G5)) | I5: =IF($A5="","", $C5-IF($E5="",0,$E5)-IF($F5="",0,$F5)+IF($G5="",0,$G5)) | J5: =IF($A5="","", $H5-$I5)
H6: =IF($A6="","", $B6+IF($D6="",0,$D6)-IF($E6="",0,$E6)-IF($F6="",0,$F6)+IF($G6="",0,$G6)) | I6: =IF($A6="","", $C6-IF($E6="",0,$E6)-IF($F6="",0,$F6)+IF($G6="",0,$G6)) | J6: =IF($A6="","", $H6-$I6)
H7: =IF($A7="","", $B7+IF($D7="",0,$D7)-IF($E7="",0,$E7)-IF($F7="",0,$F7)+IF($G7="",0,$G7)) | I7: =IF($A7="","", $C7-IF($E7="",0,$E7)-IF($F7="",0,$F7)+IF($G7="",0,$G7)) | J7: =IF($A7="","", $H7-$I7)
H8: =IF($A8="","", $B8+IF($D8="",0,$D8)-IF($E8="",0,$E8)-IF($F8="",0,$F8)+IF($G8="",0,$G8)) | I8: =IF($A8="","", $C8-IF($E8="",0,$E8)-IF($F8="",0,$F8)+IF($G8="",0,$G8)) | J8: =IF($A8="","", $H8-$I8)
H9: =IF($A9="","", $B9+IF($D9="",0,$D9)-IF($E9="",0,$E9)-IF($F9="",0,$F9)+IF($G9="",0,$G9)) | I9: =IF($A9="","", $C9-IF($E9="",0,$E9)-IF($F9="",0,$F9)+IF($G9="",0,$G9)) | J9: =IF($A9="","", $H9-$I9)
H10: =IF($A10="","", $B10+IF($D10="",0,$D10)-IF($E10="",0,$E10)-IF($F10="",0,$F10)+IF($G10="",0,$G10)) | I10: =IF($A10="","", $C10-IF($E10="",0,$E10)-IF($F10="",0,$F10)+IF($G10="",0,$G10)) | J10: =IF($A10="","", $H10-$I10)
H11: =IF($A11="","", $B11+IF($D11="",0,$D11)-IF($E11="",0,$E11)-IF($F11="",0,$F11)+IF($G11="",0,$G11)) | I11: =IF($A11="","", $C11-IF($E11="",0,$E11)-IF($F11="",0,$F11)+IF($G11="",0,$G11)) | J11: =IF($A11="","", $H11-$I11)
H12: =IF($A12="","", $B12+IF($D12="",0,$D12)-IF($E12="",0,$E12)-IF($F12="",0,$F12)+IF($G12="",0,$G12)) | I12: =IF($A12="","", $C12-IF($E12="",0,$E12)-IF($F12="",0,$F12)+IF($G12="",0,$G12)) | J12: =IF($A12="","", $H12-$I12)
H13: =IF($A13="","", $B13+IF($D13="",0,$D13)-IF($E13="",0,$E13)-IF($F13="",0,$F13)+IF($G13="",0,$G13)) | I13: =IF($A13="","", $C13-IF($E13="",0,$E13)-IF($F13="",0,$F13)+IF($G13="",0,$G13)) | J13: =IF($A13="","", $H13-$I13)
... H81: =IF($A81="","", $B81+IF($D81="",0,$D81)-IF($E81="",0,$E81)-IF($F81="",0,$F81)+IF($G81="",0,$G81)) | I81: =IF($A81="","", $C81-IF($E81="",0,$E81)-IF($F81="",0,$F81)+IF($G81="",0,$G81)) | J81: =IF($A81="","", $H81-$I81)

Sheet Arrears_Tracking
A1: As of Date | B1: Loan ID | C1: Client/Group ID | D1: Days Past Due | E1: Outstanding Balance | F1: Bucket | G1: Action Owner | H1: Next Action | I1: Status | J1: Promise To Pay Date | K1: Notes
D2: =IF($B2="","", MAXIFS(Repayment_Ledger!$J$2:$J$801,Repayment_Ledger!$A$2:$A$801,$B2)) | E2: =IF($B2="","", XLOOKUP($B2,Loan_Register!$A$2:$A$301,Loan_Register!$P$2:$P$301,"")) | F2: =IF($D2="","", IF($D2=0,"Current", IF($D2<=7,"Early", IF($D2<=30,"Watchlist", IF($D2<=90,"Serious","Critical")))))
D3: =IF($B3="","", MAXIFS(Repayment_Ledger!$J$2:$J$801,Repayment_Ledger!$A$2:$A$801,$B3)) | E3: =IF($B3="","", XLOOKUP($B3,Loan_Register!$A$2:$A$301,Loan_Register!$P$2:$P$301,"")) | F3: =IF($D3="","", IF($D3=0,"Current", IF($D3<=7,"Early", IF($D3<=30,"Watchlist", IF($D3<=90,"Serious","Critical")))))
D4: =IF($B4="","", MAXIFS(Repayment_Ledger!$J$2:$J$801,Repayment_Ledger!$A$2:$A$801,$B4)) | E4: =IF($B4="","", XLOOKUP($B4,Loan_Register!$A$2:$A$301,Loan_Register!$P$2:$P$301,"")) | F4: =IF($D4="","", IF($D4=0,"Current", IF($D4<=7,"Early", IF($D4<=30,"Watchlist", IF($D4<=90,"Serious","Critical")))))
D5: =IF($B5="","", MAXIFS(Repayment_Ledger!$J$2:$J$801,Repayment_Ledger!$A$2:$A$801,$B5)) | E5: =IF($B5="","", XLOOKUP($B5,Loan_Register!$A$2:$A$301,Loan_Register!$P$2:$P$301,"")) | F5: =IF($D5="","", IF($D5=0,"Current", IF($D5<=7,"Early", IF($D5<=30,"Watchlist", IF($D5<=90,"Serious","Critical")))))
D6: =IF($B6="","", MAXIFS(Repayment_Ledger!$J$2:$J$801,Repayment_Ledger!$A$2:$A$801,$B6)) | E6: =IF($B6="","", XLOOKUP($B6,Loan_Register!$A$2:$A$301,Loan_Register!$P$2:$P$301,"")) | F6: =IF($D6="","", IF($D6=0,"Current", IF($D6<=7,"Early", IF($D6<=30,"Watchlist", IF($D6<=90,"Serious","Critical")))))
D7: =IF($B7="","", MAXIFS(Repayment_Ledger!$J$2:$J$801,Repayment_Ledger!$A$2:$A$801,$B7)) | E7: =IF($B7="","", XLOOKUP($B7,Loan_Register!$A$2:$A$301,Loan_Register!$P$2:$P$301,"")) | F7: =IF($D7="","", IF($D7=0,"Current", IF($D7<=7,"Early", IF($D7<=30,"Watchlist", IF($D7<=90,"Serious","Critical")))))
D8: =IF($B8="","", MAXIFS(Repayment_Ledger!$J$2:$J$801,Repayment_Ledger!$A$2:$A$801,$B8)) | E8: =IF($B8="","", XLOOKUP($B8,Loan_Register!$A$2:$A$301,Loan_Register!$P$2:$P$301,"")) | F8: =IF($D8="","", IF($D8=0,"Current", IF($D8<=7,"Early", IF($D8<=30,"Watchlist", IF($D8<=90,"Serious","Critical")))))
D9: =IF($B9="","", MAXIFS(Repayment_Ledger!$J$2:$J$801,Repayment_Ledger!$A$2:$A$801,$B9)) | E9: =IF($B9="","", XLOOKUP($B9,Loan_Register!$A$2:$A$301,Loan_Register!$P$2:$P$301,"")) | F9: =IF($D9="","", IF($D9=0,"Current", IF($D9<=7,"Early", IF($D9<=30,"Watchlist", IF($D9<=90,"Serious","Critical")))))
D10: =IF($B10="","", MAXIFS(Repayment_Ledger!$J$2:$J$801,Repayment_Ledger!$A$2:$A$801,$B10)) | E10: =IF($B10="","", XLOOKUP($B10,Loan_Register!$A$2:$A$301,Loan_Register!$P$2:$P$301,"")) | F10: =IF($D10="","", IF($D10=0,"Current", IF($D10<=7,"Early", IF($D10<=30,"Watchlist", IF($D10<=90,"Serious","Critical")))))
D11: =IF($B11="","", MAXIFS(Repayment_Ledger!$J$2:$J$801,Repayment_Ledger!$A$2:$A$801,$B11)) | E11: =IF($B11="","", XLOOKUP($B11,Loan_Register!$A$2:$A$301,Loan_Register!$P$2:$P$301,"")) | F11: =IF($D11="","", IF($D11=0,"Current", IF($D11<=7,"Early", IF($D11<=30,"Watchlist", IF($D11<=90,"Serious","Critical")))))
D12: =IF($B12="","", MAXIFS(Repayment_Ledger!$J$2:$J$801,Repayment_Ledger!$A$2:$A$801,$B12)) | E12: =IF($B12="","", XLOOKUP($B12,Loan_Register!$A$2:$A$301,Loan_Register!$P$2:$P$301,"")) | F12: =IF($D12="","", IF($D12=0,"Current", IF($D12<=7,"Early", IF($D12<=30,"Watchlist", IF($D12<=90,"Serious","Critical")))))
D13: =IF($B13="","", MAXIFS(Repayment_Ledger!$J$2:$J$801,Repayment_Ledger!$A$2:$A$801,$B13)) | E13: =IF($B13="","", XLOOKUP($B13,Loan_Register!$A$2:$A$301,Loan_Register!$P$2:$P$301,"")) | F13: =IF($D13="","", IF($D13=0,"Current", IF($D13<=7,"Early", IF($D13<=30,"Watchlist", IF($D13<=90,"Serious","Critical")))))
... D401: =IF($B401="","", MAXIFS(Repayment_Ledger!$J$2:$J$801,Repayment_Ledger!$A$2:$A$801,$B401)) | E401: =IF($B401="","", XLOOKUP($B401,Loan_Register!$A$2:$A$301,Loan_Register!$P$2:$P$301,"")) | F401: =IF($D401="","", IF($D401=0,"Current", IF($D401<=7,"Early", IF($D401<=30,"Watchlist", IF($D401<=90,"Serious","Critical")))))

Sheet Reminder_Log
A1: Reminder ID | B1: Date Sent | C1: Loan ID | D1: Client ID | E1: Channel | F1: Reminder Type | G1: Due Date | H1: Amount Due | I1: Days Past Due | J1: Sent By | K1: Result | L1: Follow-up Date | M1: Notes
A2: =IF($C2="","", "REM"&TEXT(ROW()-1,"0000")) | I2: =IF($G2="","", MAX(0, TODAY()-$G2))
A3: =IF($C3="","", "REM"&TEXT(ROW()-1,"0000")) | I3: =IF($G3="","", MAX(0, TODAY()-$G3))
A4: =IF($C4="","", "REM"&TEXT(ROW()-1,"0000")) | I4: =IF($G4="","", MAX(0, TODAY()-$G4))
A5: =IF($C5="","", "REM"&TEXT(ROW()-1,"0000")) | I5: =IF($G5="","", MAX(0, TODAY()-$G5))
A6: =IF($C6="","", "REM"&TEXT(ROW()-1,"0000")) | I6: =IF($G6="","", MAX(0, TODAY()-$G6))
A7: =IF($C7="","", "REM"&TEXT(ROW()-1,"0000")) | I7: =IF($G7="","", MAX(0, TODAY()-$G7))
A8: =IF($C8="","", "REM"&TEXT(ROW()-1,"0000")) | I8: =IF($G8="","", MAX(0, TODAY()-$G8))
A9: =IF($C9="","", "REM"&TEXT(ROW()-1,"0000")) | I9: =IF($G9="","", MAX(0, TODAY()-$G9))
A10: =IF($C10="","", "REM"&TEXT(ROW()-1,"0000")) | I10: =IF($G10="","", MAX(0, TODAY()-$G10))
A11: =IF($C11="","", "REM"&TEXT(ROW()-1,"0000")) | I11: =IF($G11="","", MAX(0, TODAY()-$G11))
A12: =IF($C12="","", "REM"&TEXT(ROW()-1,"0000")) | I12: =IF($G12="","", MAX(0, TODAY()-$G12))
A13: =IF($C13="","", "REM"&TEXT(ROW()-1,"0000")) | I13: =IF($G13="","", MAX(0, TODAY()-$G13))
... A801: =IF($C801="","", "REM"&TEXT(ROW()-1,"0000")) | I801: =IF($G801="","", MAX(0, TODAY()-$G801))

Sheet Staff_Performance
A1: Staff Name | B1: Role | C1: Active Clients | D1: Loans Managed | E1: Amount Collected | F1: Due Amount (All) | G1: Collection Rate | H1: Arrears Cases (>0 days) | I1: Notes
A2: =Settings!$E2 | C2: =IF($A2="","", COUNTIF(Client_Register!$J$2:$J$301,"Active")) | D2: =IF($A2="","", COUNTIF(Loan_Register!$S$2:$S$301,$A2)) | E2: =IF($A2="","", SUMIF(Repayment_Ledger!$K$2:$K$801,$A2,Repayment_Ledger!$E$2:$E$801)) | F2: =IF($A2="","", SUMIF(Repayment_Ledger!$K$2:$K$801,$A2,Repayment_Ledger!$D$2:$D$801)) | G2: =IF($A2="","", IF($F2=0,0,$E2/$F2)) | H2: =IF($A2="","", COUNTIFS(Arrears_Tracking!$G$2:$G$401,$A2,Arrears_Tracking!$D$2:$D$401,">0"))
A3: =Settings!$E3 | C3: =IF($A3="","", COUNTIF(Client_Register!$J$2:$J$301,"Active")) | D3: =IF($A3="","", COUNTIF(Loan_Register!$S$2:$S$301,$A3)) | E3: =IF($A3="","", SUMIF(Repayment_Ledger!$K$2:$K$801,$A3,Repayment_Ledger!$E$2:$E$801)) | F3: =IF($A3="","", SUMIF(Repayment_Ledger!$K$2:$K$801,$A3,Repayment_Ledger!$D$2:$D$801)) | G3: =IF($A3="","", IF($F3=0,0,$E3/$F3)) | H3: =IF($A3="","", COUNTIFS(Arrears_Tracking!$G$2:$G$401,$A3,Arrears_Tracking!$D$2:$D$401,">0"))
A4: =Settings!$E4 | C4: =IF($A4="","", COUNTIF(Client_Register!$J$2:$J$301,"Active")) | D4: =IF($A4="","", COUNTIF(Loan_Register!$S$2:$S$301,$A4)) | E4: =IF($A4="","", SUMIF(Repayment_Ledger!$K$2:$K$801,$A4,Repayment_Ledger!$E$2:$E$801)) | F4: =IF($A4="","", SUMIF(Repayment_Ledger!$K$2:$K$801,$A4,Repayment_Ledger!$D$2:$D$801)) | G4: =IF($A4="","", IF($F4=0,0,$E4/$F4)) | H4: =IF($A4="","", COUNTIFS(Arrears_Tracking!$G$2:$G$401,$A4,Arrears_Tracking!$D$2:$D$401,">0"))
A5: =Settings!$E5 | C5: =IF($A5="","", COUNTIF(Client_Register!$J$2:$J$301,"Active")) | D5: =IF($A5="","", COUNTIF(Loan_Register!$S$2:$S$301,$A5)) | E5: =IF($A5="","", SUMIF(Repayment_Ledger!$K$2:$K$801,$A5,Repayment_Ledger!$E$2:$E$801)) | F5: =IF($A5="","", SUMIF(Repayment_Ledger!$K$2:$K$801,$A5,Repayment_Ledger!$D$2:$D$801)) | G5: =IF($A5="","", IF($F5=0,0,$E5/$F5)) | H5: =IF($A5="","", COUNTIFS(Arrears_Tracking!$G$2:$G$401,$A5,Arrears_Tracking!$D$2:$D$401,">0"))
A6: =Settings!$E6 | C6: =IF($A6="","", COUNTIF(Client_Register!$J$2:$J$301,"Active")) | D6: =IF($A6="","", COUNTIF(Loan_Register!$S$2:$S$301,$A6)) | E6: =IF($A6="","", SUMIF(Repayment_Ledger!$K$2:$K$801,$A6,Repayment_Ledger!$E$2:$E$801)) | F6: =IF($A6="","", SUMIF(Repayment_Ledger!$K$2:$K$801,$A6,Repayment_Ledger!$D$2:$D$801)) | G6: =IF($A6="","", IF($F6=0,0,$E6/$F6)) | H6: =IF($A6="","", COUNTIFS(Arrears_Tracking!$G$2:$G$401,$A6,Arrears_Tracking!$D$2:$D$401,">0"))
C7: =IF($A7="","", COUNTIF(Client_Register!$J$2:$J$301,"Active")) | D7: =IF($A7="","", COUNTIF(Loan_Register!$S$2:$S$301,$A7)) | E7: =IF($A7="","", SUMIF(Repayment_Ledger!$K$2:$K$801,$A7,Repayment_Ledger!$E$2:$E$801)) | F7: =IF($A7="","", SUMIF(Repayment_Ledger!$K$2:$K$801,$A7,Repayment_Ledger!$D$2:$D$801)) | G7: =IF($A7="","", IF($F7=0,0,$E7/$F7)) | H7: =IF($A7="","", COUNTIFS(Arrears_Tracking!$G$2:$G$401,$A7,Arrears_Tracking!$D$2:$D$401,">0"))
C8: =IF($A8="","", COUNTIF(Client_Register!$J$2:$J$301,"Active")) | D8: =IF($A8="","", COUNTIF(Loan_Register!$S$2:$S$301,$A8)) | E8: =IF($A8="","", SUMIF(Repayment_Ledger!$K$2:$K$801,$A8,Repayment_Ledger!$E$2:$E$801)) | F8: =IF($A8="","", SUMIF(Repayment_Ledger!$K$2:$K$801,$A8,Repayment_Ledger!$D$2:$D$801)) | G8: =IF($A8="","", IF($F8=0,0,$E8/$F8)) | H8: =IF($A8="","", COUNTIFS(Arrears_Tracking!$G$2:$G$401,$A8,Arrears_Tracking!$D$2:$D$401,">0"))
C9: =IF($A9="","", COUNTIF(Client_Register!$J$2:$J$301,"Active")) | D9: =IF($A9="","", COUNTIF(Loan_Register!$S$2:$S$301,$A9)) | E9: =IF($A9="","", SUMIF(Repayment_Ledger!$K$2:$K$801,$A9,Repayment_Ledger!$E$2:$E$801)) | F9: =IF($A9="","", SUMIF(Repayment_Ledger!$K$2:$K$801,$A9,Repayment_Ledger!$D$2:$D$801)) | G9: =IF($A9="","", IF($F9=0,0,$E9/$F9)) | H9: =IF($A9="","", COUNTIFS(Arrears_Tracking!$G$2:$G$401,$A9,Arrears_Tracking!$D$2:$D$401,">0"))
C10: =IF($A10="","", COUNTIF(Client_Register!$J$2:$J$301,"Active")) | D10: =IF($A10="","", COUNTIF(Loan_Register!$S$2:$S$301,$A10)) | E10: =IF($A10="","", SUMIF(Repayment_Ledger!$K$2:$K$801,$A10,Repayment_Ledger!$E$2:$E$801)) | F10: =IF($A10="","", SUMIF(Repayment_Ledger!$K$2:$K$801,$A10,Repayment_Ledger!$D$2:$D$801)) | G10: =IF($A10="","", IF($F10=0,0,$E10/$F10)) | H10: =IF($A10="","", COUNTIFS(Arrears_Tracking!$G$2:$G$401,$A10,Arrears_Tracking!$D$2:$D$401,">0"))
C11: =IF($A11="","", COUNTIF(Client_Register!$J$2:$J$301,"Active")) | D11: =IF($A11="","", COUNTIF(Loan_Register!$S$2:$S$301,$A11)) | E11: =IF($A11="","", SUMIF(Repayment_Ledger!$K$2:$K$801,$A11,Repayment_Ledger!$E$2:$E$801)) | F11: =IF($A11="","", SUMIF(Repayment_Ledger!$K$2:$K$801,$A11,Repayment_Ledger!$D$2:$D$801)) | G11: =IF($A11="","", IF($F11=0,0,$E11/$F11)) | H11: =IF($A11="","", COUNTIFS(Arrears_Tracking!$G$2:$G$401,$A11,Arrears_Tracking!$D$2:$D$401,">0"))
C12: =IF($A12="","", COUNTIF(Client_Register!$J$2:$J$301,"Active")) | D12: =IF($A12="","", COUNTIF(Loan_Register!$S$2:$S$301,$A12)) | E12: =IF($A12="","", SUMIF(Repayment_Ledger!$K$2:$K$801,$A12,Repayment_Ledger!$E$2:$E$801)) | F12: =IF($A12="","", SUMIF(Repayment_Ledger!$K$2:$K$801,$A12,Repayment_Ledger!$D$2:$D$801)) | G12: =IF($A12="","", IF($F12=0,0,$E12/$F12)) | H12: =IF($A12="","", COUNTIFS(Arrears_Tracking!$G$2:$G$401,$A12,Arrears_Tracking!$D$2:$D$401,">0"))
C13: =IF($A13="","", COUNTIF(Client_Register!$J$2:$J$301,"Active")) | D13: =IF($A13="","", COUNTIF(Loan_Register!$S$2:$S$301,$A13)) | E13: =IF($A13="","", SUMIF(Repayment_Ledger!$K$2:$K$801,$A13,Repayment_Ledger!$E$2:$E$801)) | F13: =IF($A13="","", SUMIF(Repayment_Ledger!$K$2:$K$801,$A13,Repayment_Ledger!$D$2:$D$801)) | G13: =IF($A13="","", IF($F13=0,0,$E13/$F13)) | H13: =IF($A13="","", COUNTIFS(Arrears_Tracking!$G$2:$G$401,$A13,Arrears_Tracking!$D$2:$D$401,">0"))
C14: =IF($A14="","", COUNTIF(Client_Register!$J$2:$J$301,"Active")) | D14: =IF($A14="","", COUNTIF(Loan_Register!$S$2:$S$301,$A14)) | E14: =IF($A14="","", SUMIF(Repayment_Ledger!$K$2:$K$801,$A14,Repayment_Ledger!$E$2:$E$801)) | F14: =IF($A14="","", SUMIF(Repayment_Ledger!$K$2:$K$801,$A14,Repayment_Ledger!$D$2:$D$801)) | G14: =IF($A14="","", IF($F14=0,0,$E14/$F14)) | H14: =IF($A14="","", COUNTIFS(Arrears_Tracking!$G$2:$G$401,$A14,Arrears_Tracking!$D$2:$D$401,">0"))
C15: =IF($A15="","", COUNTIF(Client_Register!$J$2:$J$301,"Active")) | D15: =IF($A15="","", COUNTIF(Loan_Register!$S$2:$S$301,$A15)) | E15: =IF($A15="","", SUMIF(Repayment_Ledger!$K$2:$K$801,$A15,Repayment_Ledger!$E$2:$E$801)) | F15: =IF($A15="","", SUMIF(Repayment_Ledger!$K$2:$K$801,$A15,Repayment_Ledger!$D$2:$D$801)) | G15: =IF($A15="","", IF($F15=0,0,$E15/$F15)) | H15: =IF($A15="","", COUNTIFS(Arrears_Tracking!$G$2:$G$401,$A15,Arrears_Tracking!$D$2:$D$401,">0"))
C16: =IF($A16="","", COUNTIF(Client_Register!$J$2:$J$301,"Active")) | D16: =IF($A16="","", COUNTIF(Loan_Register!$S$2:$S$301,$A16)) | E16: =IF($A16="","", SUMIF(Repayment_Ledger!$K$2:$K$801,$A16,Repayment_Ledger!$E$2:$E$801)) | F16: =IF($A16="","", SUMIF(Repayment_Ledger!$K$2:$K$801,$A16,Repayment_Ledger!$D$2:$D$801)) | G16: =IF($A16="","", IF($F16=0,0,$E16/$F16)) | H16: =IF($A16="","", COUNTIFS(Arrears_Tracking!$G$2:$G$401,$A16,Arrears_Tracking!$D$2:$D$401,">0"))
C17: =IF($A17="","", COUNTIF(Client_Register!$J$2:$J$301,"Active")) | D17: =IF($A17="","", COUNTIF(Loan_Register!$S$2:$S$301,$A17)) | E17: =IF($A17="","", SUMIF(Repayment_Ledger!$K$2:$K$801,$A17,Repayment_Ledger!$E$2:$E$801)) | F17: =IF($A17="","", SUMIF(Repayment_Ledger!$K$2:$K$801,$A17,Repayment_Ledger!$D$2:$D$801)) | G17: =IF($A17="","", IF($F17=0,0,$E17/$F17)) | H17: =IF($A17="","", COUNTIFS(Arrears_Tracking!$G$2:$G$401,$A17,Arrears_Tracking!$D$2:$D$401,">0"))
C18: =IF($A18="","", COUNTIF(Client_Register!$J$2:$J$301,"Active")) | D18: =IF($A18="","", COUNTIF(Loan_Register!$S$2:$S$301,$A18)) | E18: =IF($A18="","", SUMIF(Repayment_Ledger!$K$2:$K$801,$A18,Repayment_Ledger!$E$2:$E$801)) | F18: =IF($A18="","", SUMIF(Repayment_Ledger!$K$2:$K$801,$A18,Repayment_Ledger!$D$2:$D$801)) | G18: =IF($A18="","", IF($F18=0,0,$E18/$F18)) | H18: =IF($A18="","", COUNTIFS(Arrears_Tracking!$G$2:$G$401,$A18,Arrears_Tracking!$D$2:$D$401,">0"))
... C31: =IF($A31="","", COUNTIF(Client_Register!$J$2:$J$301,"Active")) | D31: =IF($A31="","", COUNTIF(Loan_Register!$S$2:$S$301,$A31)) | E31: =IF($A31="","", SUMIF(Repayment_Ledger!$K$2:$K$801,$A31,Repayment_Ledger!$E$2:$E$801)) | F31: =IF($A31="","", SUMIF(Repayment_Ledger!$K$2:$K$801,$A31,Repayment_Ledger!$D$2:$D$801)) | G31: =IF($A31="","", IF($F31=0,0,$E31/$F31)) | H31: =IF($A31="","", COUNTIFS(Arrears_Tracking!$G$2:$G$401,$A31,Arrears_Tracking!$D$2:$D$401,">0"))

Sheet KPI_Dashboard
A1: Branch KPI Dashboard
A3: KPI | B3: Value
A4: Active Clients | B4: =COUNTIF(Client_Register!$J$2:$J$301,"Active")
A5: Outstanding Portfolio | B5: =SUM(Loan_Register!$P$2:$P$301)
A6: Total Disbursed (Principal) | B6: =SUM(Loan_Register!$G$2:$G$301)
A7: Pending Applications | B7: =COUNTIF(Loan_Application_Tracker!$K$2:$K$301,"Submitted")+COUNTIF(Loan_Application_Tracker!$K$2:$K$301,"Under Review")
